{
  "id": "1811705",
  "name": "国草园智慧农业监测平台",
  "font_family": "iconfont",
  "css_prefix_text": "icon",
  "description": "",
  "glyphs": [
    {
      "icon_id": "15089290",
      "name": "bingbao ",
      "font_class": "bingbao",
      "unicode": "e611",
      "unicode_decimal": 58897
    },
    {
      "icon_id": "15089291",
      "name": "lei",
      "font_class": "lei",
      "unicode": "e612",
      "unicode_decimal": 58898
    },
    {
      "icon_id": "15089292",
      "name": "xue",
      "font_class": "xue",
      "unicode": "e613",
      "unicode_decimal": 58899
    },
    {
      "icon_id": "15089293",
      "name": "yu",
      "font_class": "yu",
      "unicode": "e614",
      "unicode_decimal": 58900
    },
    {
      "icon_id": "15089294",
      "name": "yintian",
      "font_class": "yintian",
      "unicode": "e615",
      "unicode_decimal": 58901
    },
    {
      "icon_id": "15089295",
      "name": "qing",
      "font_class": "qing",
      "unicode": "e616",
      "unicode_decimal": 58902
    },
    {
      "icon_id": "15089296",
      "name": "shachen",
      "font_class": "shachen",
      "unicode": "e617",
      "unicode_decimal": 58903
    },
    {
      "icon_id": "15089297",
      "name": "yun",
      "font_class": "yun",
      "unicode": "e618",
      "unicode_decimal": 58904
    },
    {
      "icon_id": "15089298",
      "name": "wu",
      "font_class": "wu",
      "unicode": "e619",
      "unicode_decimal": 58905
    },
    {
      "icon_id": "9862704",
      "name": "配置—前端设备配置",
      "font_class": "peizhiqianduanshebeipeizhi",
      "unicode": "e66c",
      "unicode_decimal": 58988
    },
    {
      "icon_id": "10709957",
      "name": "农机农具",
      "font_class": "nongjinongju",
      "unicode": "e65b",
      "unicode_decimal": 58971
    },
    {
      "icon_id": "11762162",
      "name": "气压",
      "font_class": "qiya",
      "unicode": "e609",
      "unicode_decimal": 58889
    },
    {
      "icon_id": "3440393",
      "name": "视频",
      "font_class": "shipin",
      "unicode": "e645",
      "unicode_decimal": 58949
    },
    {
      "icon_id": "3676215",
      "name": "配置",
      "font_class": "peizhi1",
      "unicode": "e64d",
      "unicode_decimal": 58957
    },
    {
      "icon_id": "9972033",
      "name": "预警",
      "font_class": "yujing1",
      "unicode": "e608",
      "unicode_decimal": 58888
    },
    {
      "icon_id": "13831067",
      "name": "监测数据",
      "font_class": "jianceshuju1",
      "unicode": "e6c5",
      "unicode_decimal": 59077
    },
    {
      "icon_id": "12737710",
      "name": "收缩",
      "font_class": "shousuo",
      "unicode": "e659",
      "unicode_decimal": 58969
    },
    {
      "icon_id": "4178570",
      "name": "地址",
      "font_class": "dizhi",
      "unicode": "e800",
      "unicode_decimal": 59392
    },
    {
      "icon_id": "13865636",
      "name": "文本",
      "font_class": "wenben",
      "unicode": "e620",
      "unicode_decimal": 58912
    },
    {
      "icon_id": "1226642",
      "name": "降水量",
      "font_class": "jiangshuiliang",
      "unicode": "e95a",
      "unicode_decimal": 59738
    },
    {
      "icon_id": "9343996",
      "name": "风速+",
      "font_class": "fengsu1",
      "unicode": "e6f7",
      "unicode_decimal": 59127
    },
    {
      "icon_id": "4575639",
      "name": "监测数据",
      "font_class": "jianceshuju",
      "unicode": "e666",
      "unicode_decimal": 58982
    },
    {
      "icon_id": "1745766",
      "name": "用户",
      "font_class": "yonghu",
      "unicode": "e72c",
      "unicode_decimal": 59180
    },
    {
      "icon_id": "2193744",
      "name": "土壤湿度",
      "font_class": "turangshidu",
      "unicode": "e605",
      "unicode_decimal": 58885
    },
    {
      "icon_id": "5235083",
      "name": "土壤温度",
      "font_class": "turangwendu",
      "unicode": "e61b",
      "unicode_decimal": 58907
    },
    {
      "icon_id": "5962736",
      "name": "风速",
      "font_class": "fengsu",
      "unicode": "e92b",
      "unicode_decimal": 59691
    },
    {
      "icon_id": "6756289",
      "name": "专家",
      "font_class": "zhuanjia",
      "unicode": "e607",
      "unicode_decimal": 58887
    },
    {
      "icon_id": "9144962",
      "name": "配置",
      "font_class": "peizhi",
      "unicode": "e603",
      "unicode_decimal": 58883
    },
    {
      "icon_id": "9295755",
      "name": "湿度",
      "font_class": "shidu",
      "unicode": "e63e",
      "unicode_decimal": 58942
    },
    {
      "icon_id": "10680317",
      "name": "云量",
      "font_class": "yunliang",
      "unicode": "e6ee",
      "unicode_decimal": 59118
    },
    {
      "icon_id": "10806575",
      "name": "紫外线",
      "font_class": "ziwaixian",
      "unicode": "e604",
      "unicode_decimal": 58884
    },
    {
      "icon_id": "11182123",
      "name": "能见度",
      "font_class": "nengjiandu",
      "unicode": "e6a9",
      "unicode_decimal": 59049
    },
    {
      "icon_id": "13363292",
      "name": "控制",
      "font_class": "kongzhi",
      "unicode": "e606",
      "unicode_decimal": 58886
    },
    {
      "icon_id": "13982230",
      "name": "预警",
      "font_class": "yujing",
      "unicode": "e60b",
      "unicode_decimal": 58891
    },
    {
      "icon_id": "14204374",
      "name": "光照强度",
      "font_class": "guangzhaoqiangdu",
      "unicode": "e767",
      "unicode_decimal": 59239
    },
    {
      "icon_id": "3025233",
      "name": "监控",
      "font_class": "jiankong",
      "unicode": "e669",
      "unicode_decimal": 58985
    },
    {
      "icon_id": "3340956",
      "name": "植物",
      "font_class": "zhiwu",
      "unicode": "e600",
      "unicode_decimal": 58880
    },
    {
      "icon_id": "4652701",
      "name": "空气温度",
      "font_class": "kongqiwendu",
      "unicode": "e602",
      "unicode_decimal": 58882
    },
    {
      "icon_id": "9843321",
      "name": "地图",
      "font_class": "ditu",
      "unicode": "e631",
      "unicode_decimal": 58929
    },
    {
      "icon_id": "9970032",
      "name": "空气",
      "font_class": "kongqi",
      "unicode": "e77b",
      "unicode_decimal": 59259
    },
    {
      "icon_id": "12521369",
      "name": "空气湿度",
      "font_class": "kongqishidu",
      "unicode": "e70d",
      "unicode_decimal": 59149
    },
    {
      "icon_id": "12943201",
      "name": "删 除",
      "font_class": "shanchu",
      "unicode": "e62e",
      "unicode_decimal": 58926
    },
    {
      "icon_id": "13383009",
      "name": "查看",
      "font_class": "chakan",
      "unicode": "e60a",
      "unicode_decimal": 58890
    },
    {
      "icon_id": "13682452",
      "name": "土壤",
      "font_class": "turanghuanjing",
      "unicode": "e957",
      "unicode_decimal": 59735
    },
    {
      "icon_id": "13815704",
      "name": "修 改",
      "font_class": "xiugai",
      "unicode": "e601",
      "unicode_decimal": 58881
    },
    {
      "icon_id": "13837385",
      "name": "虫情监测 - 简",
      "font_class": "chongqingjiance-jian",
      "unicode": "e776",
      "unicode_decimal": 59254
    }
  ]
}
